{"cameraMode":{"drawMode":0,"name":"Shaded","section":"Shading Mode"},"sceneLighting":false,"audioPlay":false,"sceneViewState":{"showFog":true,"showMaterialUpdate":false,"showSkybox":false,"showFlares":true,"showImageEffects":true,"showParticleSystems":true},"in2DMode":false,"pivot":{"x":-2.9802322387695315e-8,"y":0.5,"z":-8.940696716308594e-8},"rotation":{"x":-0.3568570911884308,"y":-0.3208180367946625,"z":0.1319863647222519,"w":-0.8673571944236755},"size":1.7147303819656373,"orthographic":false}